celery_inspect/__init__.py
celery_inspect/admin.py
celery_inspect/apps.py
celery_inspect/models.py
celery_inspect/test_api.py
celery_inspect/urls.py
celery_inspect/views.py
celery_inspect/api/__init__.py
celery_inspect/api/viewsets.py
celery_inspect/migrations/__init__.py
django_celery_inspect-0.2.1.dist-info/DESCRIPTION.rst
django_celery_inspect-0.2.1.dist-info/LICENSE.txt
django_celery_inspect-0.2.1.dist-info/METADATA
django_celery_inspect-0.2.1.dist-info/RECORD
django_celery_inspect-0.2.1.dist-info/WHEEL
django_celery_inspect-0.2.1.dist-info/metadata.json
django_celery_inspect-0.2.1.dist-info/top_level.txt
