Metadata-Version: 2.0
Name: django-celery-inspect
Version: 0.2.1
Summary: Django Reusable app that uses Celery Inspect command to monitor workers/tasks via the Django REST Framework
Home-page: https://github.com/psychok7/django-celery-inspect
Author: Nuno Khan
Author-email: nunok7@gmail.com
License: MIT
Download-URL: https://github.com/psychok7/django-celery-inspect/tarball/v0.2.1
Keywords: django,django-rest-framework,celery,inspection,monitoring,python
Platform: UNKNOWN
Classifier: Development Status :: 5 - Production/Stable
Classifier: Intended Audience :: Developers
Classifier: Topic :: Software Development :: Build Tools
Classifier: License :: OSI Approved :: MIT License
Classifier: Framework :: Django :: 1.8
Classifier: Framework :: Django :: 1.9
Classifier: Framework :: Django :: 1.10
Classifier: Programming Language :: Python :: 2.7
Classifier: Programming Language :: Python :: 3
Classifier: Programming Language :: Python :: 3.2
Classifier: Programming Language :: Python :: 3.3
Classifier: Programming Language :: Python :: 3.4
Classifier: Programming Language :: Python :: 3.5
Requires-Dist: celery (>=3.0)
Requires-Dist: djangorestframework (>=3.3.1)
